{
  "data": [
    {
      "id": 1,
      "name": "Brian Franklin",
      "createDate": "2018/03/04",
      "status": "<i class='icon-checkbox-marked-circle green-500-fg'></i>",
      "view": "<i class='icon-pencil'></i>"
    },
    {
      "id": 2,
      "name": "AK",
      "createDate": "2018/03/12",
      "status": "<i class='icon-checkbox-marked-circle green-500-fg'></i>",
      "view": "<i class='icon-pencil'></i>"
    },
    {
      "id": 3,
      "name": "CK",
      "createDate": "2018/03/05",
      "status": "<i class='icon-cancel red-500-fg'></i>",
      "view": "<i class='icon-pencil'></i>"
    },
    {
      "id": 4,
      "name": "KK",
      "createDate": "2018/03/08",
      "status": "<i class='icon-checkbox-marked-circle green-500-fg'></i>",
      "view": "<i class='icon-pencil'></i>"
    },
    {
      "id": 5,
      "name": "PK",
      "createDate": "2018/03/28",
      "status": "<i class='icon-cancel red-500-fg'></i>",
      "view": "<i class='icon-pencil'></i>"
    },
    {
      "id": 6,
      "name": "MSD",
      "createDate": "2018/04/04",
      "status": "<i class='icon-checkbox-marked-circle green-500-fg'></i>",
      "view": "<i class='icon-pencil'></i>"
    },
    {
      "id": 7,
      "name": "Dhoni",
      "createDate": "2018/04/12",
      "status": "<i class='icon-checkbox-marked-circle green-500-fg'></i>",
      "view": "<i class='icon-pencil'></i>"
    },
    {
      "id": 8,
      "name": "CSK",
      "createDate": "2018/04/05",
      "status": "<i class='icon-cancel red-500-fg'></i>",
      "view": "<i class='icon-pencil'></i>"
    },
    {
      "id": 9,
      "name": "Kholi",
      "createDate": "2018/03/25",
      "status": "<i class='icon-checkbox-marked-circle green-500-fg'></i>",
      "view": "<i class='icon-pencil'></i>"
    },
    {
      "id": 10,
      "name": "ABD",
      "createDate": "2018/03/15",
      "status": "<i class='icon-cancel red-500-fg'></i>",
      "view": "<i class='icon-pencil'></i>"
    },{
      "id": 11,
      "name": "dhinesh",
      "createDate": "2018/03/11",
      "status": "<i class='icon-checkbox-marked-circle green-500-fg'></i>",
      "view": "<i class='icon-pencil'></i>"
    },
    {
      "id": 12,
      "name": "chandru",
      "createDate": "2018/04/20",
      "status": "<i class='icon-checkbox-marked-circle green-500-fg'></i>",
      "view": "<i class='icon-pencil'></i>"
    },
    {
      "id": 13,
      "name": "saravana",
      "createDate": "2018/04/22",
      "status": "<i class='icon-cancel red-500-fg'></i>",
      "view": "<i class='icon-pencil'></i>"
    },
    {
      "id": 14,
      "name": "yoga",
      "createDate": "2018/04/18",
      "status": "<i class='icon-checkbox-marked-circle green-500-fg'></i>",
      "view": "<i class='icon-pencil'></i>"
    },
    {
      "id": 15,
      "name": "hari",
      "createDate": "2018/04/26",
      "status": "<i class='icon-cancel red-500-fg'></i>",
      "view": "<i class='icon-pencil'></i>"
    },{
      "id": 16,
      "name": "Brian lara",
      "createDate": "2018/04/24",
      "status": "<i class='icon-checkbox-marked-circle green-500-fg'></i>",
      "view": "<i class='icon-pencil'></i>"
    },{
      "id": 17,
      "name": "Franklin",
      "createDate": "2018/03/13",
      "status": "<i class='icon-checkbox-marked-circle green-500-fg'></i>",
      "view": "<i class='icon-pencil'></i>"
    },
    {
      "id": 18,
      "name": "Avengers",
      "createDate": "2018/03/16",
      "status": "<i class='icon-checkbox-marked-circle green-500-fg'></i>",
      "view": "<i class='icon-pencil'></i>"
    },
    {
      "id": 19,
      "name": "thor",
      "createDate": "2018/03/17",
      "status": "<i class='icon-cancel red-500-fg'></i>",
      "view": "<i class='icon-pencil'></i>"
    },
    {
      "id": 20,
      "name": "ultron",
      "createDate": "2018/03/29",
      "status": "<i class='icon-checkbox-marked-circle green-500-fg'></i>",
      "view": "<i class='icon-pencil'></i>"
    },
    {
      "id": 21,
      "name": "Tony",
      "createDate": "2018/03/30",
      "status": "<i class='icon-cancel red-500-fg'></i>",
      "view": "<i class='icon-pencil'></i>"
    },{
      "id": 22,
      "name": "Stark",
      "createDate": "2018/04/30",
      "status": "<i class='icon-checkbox-marked-circle green-500-fg'></i>",
      "view": "<i class='icon-pencil'></i>"
    },
    {
      "id": 23,
      "name": "toretto",
      "createDate": "2018/03/27",
      "status": "<i class='icon-checkbox-marked-circle green-500-fg'></i>",
      "view": "<i class='icon-pencil'></i>"
    },
    {
      "id": 24,
      "name": "jack",
      "createDate": "2018/04/27",
      "status": "<i class='icon-cancel red-500-fg'></i>",
      "view": "<i class='icon-pencil'></i>"
    },
    {
      "id": 25,
      "name": "customer",
      "createDate": "2018/05/08",
      "status": "<i class='icon-checkbox-marked-circle green-500-fg'></i>",
      "view": "<i class='icon-pencil'></i>"
    },
    {
      "id": 26,
      "name": "person",
      "createDate": "2018/05/28",
      "status": "<i class='icon-cancel red-500-fg'></i>",
      "view": "<i class='icon-pencil'></i>"
    },{
      "id": 27,
      "name": "frank",
      "createDate": "2018/05/04",
      "status": "<i class='icon-checkbox-marked-circle green-500-fg'></i>",
      "view": "<i class='icon-pencil'></i>"
    },
    {
      "id": 28,
      "name": "turtle",
      "createDate": "2018/05/12",
      "status": "<i class='icon-checkbox-marked-circle green-500-fg'></i>",
      "view": "<i class='icon-pencil'></i>"
    },
    {
      "id": 29,
      "name": "elephant",
      "createDate": "2018/05/05",
      "status": "<i class='icon-cancel red-500-fg'></i>",
      "view": "<i class='icon-pencil'></i>"
    },
    {
      "id": 30,
      "name": "tiger",
      "createDate": "2018/05/08",
      "status": "<i class='icon-checkbox-marked-circle green-500-fg'></i>",
      "view": "<i class='icon-pencil'></i>"
    },
    {
      "id": 31,
      "name": "Lion",
      "createDate": "2018/05/28",
      "status": "<i class='icon-cancel red-500-fg'></i>",
      "view": "<i class='icon-pencil'></i>"
    }
  ]
}
